ursactl/__init__.py
ursactl/main.py
ursactl/airflow_provider/__init__.py
ursactl/airflow_provider/hooks.py
ursactl/controllers/__init__.py
ursactl/controllers/base.py
ursactl/controllers/create.py
ursactl/controllers/delete.py
ursactl/controllers/get.py
ursactl/controllers/init.py
ursactl/controllers/list.py
ursactl/controllers/refresh.py
ursactl/controllers/run.py
ursactl/controllers/send.py
ursactl/controllers/show.py
ursactl/controllers/stop.py
ursactl/controllers/sync.py
ursactl/controllers/update.py
ursactl/controllers/utils/__init__.py
ursactl/controllers/utils/packages.py
ursactl/controllers/utils/pages.py
ursactl/controllers/utils/transforms.py
ursactl/core/__init__.py
ursactl/core/_base.py
ursactl/core/agent.py
ursactl/core/agent_swarm.py
ursactl/core/dataset.py
ursactl/core/exc.py
ursactl/core/handlers.py
ursactl/core/pipeline.py
ursactl/core/pipeline_run.py
ursactl/core/pipeline_sweep.py
ursactl/core/project.py
ursactl/core/running_agent.py
ursactl/core/version.py
ursactl/core/services/__init__.py
ursactl/core/services/_base.py
ursactl/core/services/ape_client.py
ursactl/core/services/dss_client.py
ursactl/core/services/iam_client.py
ursactl/core/services/page_client.py
ursactl/core/services/planning_client.py
ursactl/core/services/project_client.py
ursactl/core/services/async_client/__init__.py
ursactl/core/services/async_client/client.py
ursactl/core/services/async_client/messages.py
ursactl/core/services/async_client/socket.py
ursactl/core/services/async_client/transport.py
ursactl/core/services/async_client/utils.py
ursactl/core/utils/__init__.py
ursactl/core/utils/magic.py
ursactl/ext/__init__.py
ursactl/plugins/__init__.py
ursactl/templates/__init__.py
ursactl-0.10.0.dist-info/LICENSE.md
ursactl-0.10.0.dist-info/METADATA
ursactl-0.10.0.dist-info/WHEEL
ursactl-0.10.0.dist-info/entry_points.txt
ursactl-0.10.0.dist-info/top_level.txt
ursactl-0.10.0.dist-info/zip-safe
ursactl-0.10.0.dist-info/RECORD
