Metadata-Version: 2.1
Name: ursactl
Version: 0.10.0
Summary: command line tool and library for intercting with ursafrontier.cloud
Home-page: https://ursafrontier.cloud/
Author: Ursa Frontier LLC
Author-email: contact@ursafrontier.com
Classifier: Development Status :: 3 - Alpha
Classifier: Environment :: Console
Classifier: Intended Audience :: Developers
Classifier: Intended Audience :: Science/Research
Classifier: License :: Other/Proprietary License
Classifier: Operating System :: OS Independent
Classifier: Programming Language :: Python :: 3
Classifier: Programming Language :: Python :: 3.7
Classifier: Programming Language :: Python :: 3.8
Classifier: Programming Language :: Python :: 3.9
Classifier: Programming Language :: Python :: 3.10
Classifier: Programming Language :: Python :: 3.11
Classifier: Topic :: Scientific/Engineering
Classifier: Topic :: Scientific/Engineering :: Artificial Intelligence
Classifier: Topic :: Scientific/Engineering :: Information Analysis
Requires-Python: >=3.7
License-File: LICENSE.md
Requires-Dist: cement
Requires-Dist: cement[jinja2]
Requires-Dist: cement[colorlog]
Requires-Dist: cement[tabulate]
Requires-Dist: gql >=3.4.0
Requires-Dist: jsonschema >=4.17.3
Requires-Dist: lupa >=2.0
Requires-Dist: python-graphql-client >=0.4.3
Requires-Dist: python-hcl2 >=4.3.0
Requires-Dist: pyYAML >=6.0
Requires-Dist: requests >=2.28.1
Requires-Dist: rich >=13.0.0
Requires-Dist: tinydb >=4.7.0
